{
  "id": 12,
  "level": "N3",
  "category": "N3 여행",
  "title": "여행 N3 100문장",
  "mode": "DRILL",
  "sentences": [
    {
      "id": 1,
      "jp": "天気予報によると、明日は台風が来るそうです。",
      "kr": "일기예보에 따르면 내일은 태풍이 온다고 합니다.",
      "words": [
        {
          "jp": "天気予報",
          "kr": "일기예보"
        },
        {
          "jp": "～によると",
          "kr": "～에 따르면"
        },
        {
          "jp": "～そうだ",
          "kr": "～라고 한다"
        }
      ]
    },
    {
      "id": 2,
      "jp": "パスポートを忘れないように、かばんに入れておいた。",
      "kr": "여권을 잊지 않도록 가방에 넣어 두었다.",
      "words": [
        {
          "jp": "パスポート",
          "kr": "여권"
        }
      ]
    },
    {
      "id": 3,
      "jp": "予約しておいたおかげで、待たずに入れました。",
      "kr": "미리 예약해 둔 덕분에 기다리지 않고 들어갈 수 있었습니다.",
      "words": [
        {
          "jp": "～おかげで",
          "kr": "～덕분에"
        },
        {
          "jp": "～ずに",
          "kr": "～하지 않고"
        }
      ]
    },
    {
      "id": 4,
      "jp": "この地図を見れば、駅までの道が分かるはずです。",
      "kr": "이 지도를 보면 역까지 가는 길을 알 수 있을 겁니다.",
      "words": [
        {
          "jp": "～はずだ",
          "kr": "～할 것이다, ～일 것이다"
        }
      ]
    },
    {
      "id": 5,
      "jp": "電車が遅れたせいで、飛行機に乗り遅れた。",
      "kr": "전철이 늦은 탓에 비행기를 놓쳤다.",
      "words": [
        {
          "jp": "～せいで",
          "kr": "～탓에"
        },
        {
          "jp": "乗り遅れる",
          "kr": "(차를) 놓치다"
        }
      ]
    },
    {
      "id": 6,
      "jp": "旅行に行くたびに、その土地の料理を食べることにしています。",
      "kr": "여행을 갈 때마다 그 지역의 음식을 먹기로 하고 있습니다.",
      "words": [
        {
          "jp": "～たびに",
          "kr": "～할 때마다"
        },
        {
          "jp": "土地",
          "kr": "고장, 지방"
        },
        {
          "jp": "～ことにしている",
          "kr": "～하기로 하고 있다"
        }
      ]
    },
    {
      "id": 7,
      "jp": "ホテルの部屋から海が見えて、部屋も思ったより広かったです。",
      "kr": "호텔 방에서 바다가 보였고, 방도 생각보다 넓었습니다.",
      "words": [
        {
          "jp": "思ったより",
          "kr": "생각보다"
        }
      ]
    },
    {
      "id": 8,
      "jp": "道に迷ってしまったので、近くの人に聞いてみました。",
      "kr": "길을 잃어서 근처 사람에게 물어보았습니다.",
      "words": [
        {
          "jp": "道に迷う",
          "kr": "길을 잃다"
        }
      ]
    },
    {
      "id": 9,
      "jp": "荷物が多すぎて、一人では運びきれません。",
      "kr": "짐이 너무 많아서 혼자서는 다 옮길 수 없습니다.",
      "words": [
        {
          "jp": "運ぶ",
          "kr": "옮기다"
        },
        {
          "jp": "～きれない",
          "kr": "다 ～할 수 없다"
        }
      ]
    },
    {
      "id": 10,
      "jp": "現地の言葉が話せなくても、身振りで何とかなります。",
      "kr": "현지 말을 하지 못해도 몸짓으로 어떻게든 해결할 수 있습니다.",
      "words": [
        {
          "jp": "現地",
          "kr": "현지"
        },
        {
          "jp": "身振り",
          "kr": "몸짓"
        },
        {
          "jp": "何とかなる",
          "kr": "어떻게든 되다"
        }
      ]
    },
    {
      "id": 11,
      "jp": "せっかく来たのだから、有名なお寺を見て行こう。",
      "kr": "모처럼 왔으니 유명한 절을 보고 가자.",
      "words": [
        {
          "jp": "せっかく",
          "kr": "모처럼"
        }
      ]
    },
    {
      "id": 12,
      "jp": "チケットは、インターネットで買っておくと安いです。",
      "kr": "티켓은 인터넷으로 미리 사 두면 저렴합니다.",
      "words": [
        {
          "jp": "チケット",
          "kr": "티켓"
        },
        {
          "jp": "～ておく",
          "kr": "미리 ～해 두다"
        }
      ]
    },
    {
      "id": 13,
      "jp": "この電車は、乗り換えなしで空港まで行けるらしいです。",
      "kr": "이 전철은 환승 없이 공항까지 갈 수 있다고 합니다.",
      "words": [
        {
          "jp": "乗り換え",
          "kr": "환승"
        },
        {
          "jp": "～らしい",
          "kr": "～인 듯하다, ～라고 한다"
        }
      ]
    },
    {
      "id": 14,
      "jp": "雨が降りそうだから、傘を持って行ったほうがいいですよ。",
      "kr": "비가 올 것 같으니 우산을 가져가는 편이 좋아요.",
      "words": [
        {
          "jp": "～そうだ",
          "kr": "～할 것 같다"
        }
      ]
    },
    {
      "id": 15,
      "jp": "予定通りに行けば、昼までには着くでしょう。",
      "kr": "예정대로 가면 정오까지는 도착할 것입니다.",
      "words": [
        {
          "jp": "～通りに",
          "kr": "～대로"
        }
      ]
    },
    {
      "id": 16,
      "jp": "外国を旅行しているうちに、その国が好きになりました。",
      "kr": "외국을 여행하는 동안 그 나라를 좋아하게 되었습니다.",
      "words": [
        {
          "jp": "～うちに",
          "kr": "～하는 동안에"
        }
      ]
    },
    {
      "id": 17,
      "jp": "この温泉は、体にいいと言われています。",
      "kr": "이 온천은 몸에 좋다고 알려져 있습니다.",
      "words": [
        {
          "jp": "温泉",
          "kr": "온천"
        },
        {
          "jp": "～と言われている",
          "kr": "～라고 알려져 있다"
        }
      ]
    },
    {
      "id": 18,
      "jp": "道が混んでいるので、電車で行くしかありません。",
      "kr": "길이 막혀 있어서 전철로 갈 수밖에 없습니다.",
      "words": [
        {
          "jp": "混む",
          "kr": "붐비다, 막히다"
        },
        {
          "jp": "～しかない",
          "kr": "～할 수밖에 없다"
        }
      ]
    },
    {
      "id": 19,
      "jp": "パンフレットに書いてある通りに回ってみました。",
      "kr": "팸플릿에 적혀 있는 대로 둘러보았습니다.",
      "words": [
        {
          "jp": "パンフレット",
          "kr": "팸플릿"
        },
        {
          "jp": "回る",
          "kr": "돌아보다, 둘러보다"
        }
      ]
    },
    {
      "id": 20,
      "jp": "飛行機の中で寝ていたら、いつの間にか到着していました。",
      "kr": "비행기 안에서 자고 있었더니 어느새 도착해 있었습니다.",
      "words": [
        {
          "jp": "いつの間にか",
          "kr": "어느새"
        },
        {
          "jp": "到着",
          "kr": "도착"
        }
      ]
    },
    {
      "id": 21,
      "jp": "観光客が増えるにつれて、町がにぎやかになりました。",
      "kr": "관광객이 늘어남에 따라 마을이 활기차졌습니다.",
      "words": [
        {
          "jp": "観光客",
          "kr": "관광객"
        },
        {
          "jp": "～につれて",
          "kr": "～함에 따라"
        },
        {
          "jp": "にぎやか",
          "kr": "활기차다, 북적이다"
        }
      ]
    },
    {
      "id": 22,
      "jp": "有名な店だけあって、行列ができていました。",
      "kr": "유명한 가게인 만큼 긴 줄이 늘어서 있었습니다.",
      "words": [
        {
          "jp": "～だけあって",
          "kr": "～인 만큼"
        },
        {
          "jp": "行列",
          "kr": "줄, 대기 행렬"
        }
      ]
    },
    {
      "id": 23,
      "jp": "現金しか使えない店もあるので、注意が必要です。",
      "kr": "현금만 사용할 수 있는 가게도 있으므로 주의가 필요합니다.",
      "words": [
        {
          "jp": "現金",
          "kr": "현금"
        },
        {
          "jp": "～しか～ない",
          "kr": "～밖에 ～없다"
        }
      ]
    },
    {
      "id": 24,
      "jp": "天気さえよければ、山に登るつもりだ。",
      "kr": "날씨만 좋으면 산에 오를 생각이다.",
      "words": [
        {
          "jp": "～さえ～ば",
          "kr": "～만 ～하면"
        },
        {
          "jp": "登る",
          "kr": "오르다"
        }
      ]
    },
    {
      "id": 25,
      "jp": "この橋は、百年前に作られたそうです。",
      "kr": "이 다리는 100년 전에 만들어졌다고 합니다.",
      "words": [
        {
          "jp": "～そうだ",
          "kr": "～라고 한다"
        }
      ]
    },
    {
      "id": 26,
      "jp": "スーツケースが重くて、持ち上げられませんでした。",
      "kr": "여행 가방이 무거워서 들어 올릴 수 없었습니다.",
      "words": [
        {
          "jp": "スーツケース",
          "kr": "여행 가방"
        },
        {
          "jp": "持ち上げる",
          "kr": "들어 올리다"
        }
      ]
    },
    {
      "id": 27,
      "jp": "どこに行くか、まだ決めていません。",
      "kr": "어디에 갈지 아직 정하지 않았습니다.",
      "words": [
        {
          "jp": "まだ",
          "kr": "아직"
        },
        {
          "jp": "決める",
          "kr": "정하다"
        }
      ]
    },
    {
      "id": 28,
      "jp": "予約をキャンセルする場合は、前日までに連絡してください。",
      "kr": "예약을 취소하는 경우에는 전날까지 연락해 주세요.",
      "words": [
        {
          "jp": "～場合",
          "kr": "～경우"
        },
        {
          "jp": "前日",
          "kr": "전날"
        }
      ]
    },
    {
      "id": 29,
      "jp": "迷わないように、地図アプリを使うことにしました。",
      "kr": "헤매지 않도록 지도 앱을 사용하기로 했습니다.",
      "words": [
        {
          "jp": "迷う",
          "kr": "헤매다"
        }
      ]
    },
    {
      "id": 30,
      "jp": "旅の疲れが出たのか、一日中眠かったです。",
      "kr": "여행 피로가 몰려온 건지 하루 종일 졸렸습니다.",
      "words": [
        {
          "jp": "疲れが出る",
          "kr": "피로가 나타나다"
        },
        {
          "jp": "一日中",
          "kr": "하루 종일"
        }
      ]
    },
    {
      "id": 31,
      "jp": "飛行機のチケットが取れなくて、旅行を延期しました。",
      "kr": "비행기표를 구하지 못해서 여행을 연기했습니다.",
      "words": [
        {
          "jp": "取れる",
          "kr": "구해지다"
        },
        {
          "jp": "延期",
          "kr": "연기"
        }
      ]
    },
    {
      "id": 32,
      "jp": "海外に行くなら、保険に入っておいたほうがいいですよ。",
      "kr": "해외에 간다면 보험에 미리 들어 두는 편이 좋아요.",
      "words": [
        {
          "jp": "海外",
          "kr": "해외"
        },
        {
          "jp": "保険に入る",
          "kr": "보험에 들다"
        }
      ]
    },
    {
      "id": 33,
      "jp": "せっかくの旅行なのに、ずっと雨で残念でした。",
      "kr": "모처럼 떠난 여행인데 계속 비가 와서 아쉬웠습니다.",
      "words": [
        {
          "jp": "せっかく",
          "kr": "모처럼"
        },
        {
          "jp": "残念",
          "kr": "아쉬움, 유감"
        }
      ]
    },
    {
      "id": 34,
      "jp": "ガイドブックによると、この店は地元で有名らしいです。",
      "kr": "가이드북에 따르면 이 가게는 현지에서 유명하다고 합니다.",
      "words": [
        {
          "jp": "～によると",
          "kr": "～에 따르면"
        },
        {
          "jp": "地元",
          "kr": "현지, 그 지역"
        },
        {
          "jp": "～らしい",
          "kr": "～라고 한다"
        }
      ]
    },
    {
      "id": 35,
      "jp": "道を間違えたおかげで、きれいな景色に出会えました。",
      "kr": "길을 잘못 든 덕분에 아름다운 경치를 만날 수 있었습니다.",
      "words": [
        {
          "jp": "間違える",
          "kr": "틀리다, 잘못하다"
        },
        {
          "jp": "景色",
          "kr": "경치"
        },
        {
          "jp": "出会う",
          "kr": "만나다"
        }
      ]
    },
    {
      "id": 36,
      "jp": "荷物を預けておけば、身軽に観光できます。",
      "kr": "짐을 맡겨 두면 가볍게 관광할 수 있습니다.",
      "words": [
        {
          "jp": "預ける",
          "kr": "맡기다"
        },
        {
          "jp": "身軽",
          "kr": "몸이 가벼움, 홀가분함"
        },
        {
          "jp": "観光",
          "kr": "관광"
        }
      ]
    },
    {
      "id": 37,
      "jp": "電車の時間を調べておかないと、乗り遅れます。",
      "kr": "전철 시간을 미리 확인해 두지 않으면 놓칠 수 있습니다.",
      "words": [
        {
          "jp": "調べる",
          "kr": "알아보다, 조사하다"
        },
        {
          "jp": "～ないと",
          "kr": "～하지 않으면"
        },
        {
          "jp": "乗り遅れる",
          "kr": "(차를) 놓치다"
        }
      ]
    },
    {
      "id": 38,
      "jp": "この道をまっすぐ行けば、駅に着くはずです。",
      "kr": "이 길을 곧장 가면 역에 도착할 겁니다.",
      "words": [
        {
          "jp": "～はずだ",
          "kr": "～할 것이다"
        }
      ]
    },
    {
      "id": 39,
      "jp": "旅行に行くなら、天気を確認してから出発しよう。",
      "kr": "여행 갈 거면 날씨를 확인하고 나서 출발하자.",
      "words": [
        {
          "jp": "確認",
          "kr": "확인"
        },
        {
          "jp": "～てから",
          "kr": "～하고 나서"
        },
        {
          "jp": "出発する",
          "kr": "출발하다"
        }
      ]
    },
    {
      "id": 40,
      "jp": "現地の食べ物は、思ったよりおいしかったです。",
      "kr": "현지 음식은 생각보다 맛있었습니다.",
      "words": [
        {
          "jp": "現地",
          "kr": "현지"
        },
        {
          "jp": "思ったより",
          "kr": "생각보다"
        }
      ]
    },
    {
      "id": 41,
      "jp": "予約したホテルは、駅から近くて便利でした。",
      "kr": "예약한 호텔은 역에서 가까워서 편리했습니다.",
      "words": [
        {
          "jp": "予約",
          "kr": "예약"
        },
        {
          "jp": "便利",
          "kr": "편리"
        }
      ]
    },
    {
      "id": 42,
      "jp": "山道は険しくて、登るのに苦労しました。",
      "kr": "산길은 험해서 오르는 데 고생했습니다.",
      "words": [
        {
          "jp": "山道",
          "kr": "산길"
        },
        {
          "jp": "険しい",
          "kr": "험하다"
        },
        {
          "jp": "苦労",
          "kr": "고생"
        }
      ]
    },
    {
      "id": 43,
      "jp": "旅先で財布をなくして、大変な目にあいました。",
      "kr": "여행지에서 지갑을 잃어버려서 곤란한 일을 겪었습니다.",
      "words": [
        {
          "jp": "旅先",
          "kr": "여행지"
        },
        {
          "jp": "なくす",
          "kr": "잃어버리다"
        },
        {
          "jp": "～目にあう",
          "kr": "～한 일을 당하다, 겪다"
        }
      ]
    },
    {
      "id": 44,
      "jp": "天気次第では、予定を変更するかもしれません。",
      "kr": "날씨에 따라서는 일정을 변경할지도 모릅니다.",
      "words": [
        {
          "jp": "～次第では",
          "kr": "～에 따라서는"
        },
        {
          "jp": "変更",
          "kr": "변경"
        }
      ]
    },
    {
      "id": 45,
      "jp": "荷物が多いので、タクシーを呼ぶことにしました。",
      "kr": "짐이 많아서 택시를 부르기로 했습니다.",
      "words": [
        {
          "jp": "呼ぶ",
          "kr": "부르다"
        },
        {
          "jp": "～ことにする",
          "kr": "～하기로 하다"
        }
      ]
    },
    {
      "id": 46,
      "jp": "観光地はどこも人でいっぱいでした。",
      "kr": "관광지는 어디나 사람들로 가득했습니다.",
      "words": [
        {
          "jp": "観光地",
          "kr": "관광지"
        }
      ]
    },
    {
      "id": 47,
      "jp": "現地の言葉が分からなくても、笑顔で気持ちが通じました。",
      "kr": "현지 말을 몰라도 미소로 마음이 통했습니다.",
      "words": [
        {
          "jp": "笑顔",
          "kr": "미소"
        },
        {
          "jp": "通じる",
          "kr": "통하다"
        }
      ]
    },
    {
      "id": 48,
      "jp": "この温泉は、肌にいいと言われています。",
      "kr": "이 온천은 피부에 좋다고 알려져 있습니다.",
      "words": [
        {
          "jp": "肌",
          "kr": "피부"
        },
        {
          "jp": "～と言われている",
          "kr": "～라고 알려져 있다"
        }
      ]
    },
    {
      "id": 49,
      "jp": "飛行機がひどく揺れて、少し怖かったです。",
      "kr": "비행기가 심하게 흔들려서 조금 무서웠습니다.",
      "words": [
        {
          "jp": "揺れる",
          "kr": "흔들리다"
        },
        {
          "jp": "ひどく",
          "kr": "심하게"
        }
      ]
    },
    {
      "id": 50,
      "jp": "早く着きすぎて、開店まで待つことになりました。",
      "kr": "너무 일찍 도착해서 개점할 때까지 기다리게 되었습니다.",
      "words": [
        {
          "jp": "開店",
          "kr": "개점"
        },
        {
          "jp": "待たされる",
          "kr": "기다리게 되다, 기다려야 하다"
        }
      ]
    },
    {
      "id": 51,
      "jp": "パンフレットをもらったので、あとで読んでみます。",
      "kr": "팸플릿을 받았으니 나중에 읽어 보겠습니다.",
      "words": [
        {
          "jp": "もらう",
          "kr": "받다"
        },
        {
          "jp": "～てみる",
          "kr": "～해 보다"
        }
      ]
    },
    {
      "id": 52,
      "jp": "予定より早く着いたので、少し散歩しました。",
      "kr": "예정보다 일찍 도착해서 잠시 산책했습니다.",
      "words": [
        {
          "jp": "予定",
          "kr": "예정"
        },
        {
          "jp": "着く",
          "kr": "도착하다"
        },
        {
          "jp": "散歩",
          "kr": "산책"
        }
      ]
    },
    {
      "id": 53,
      "jp": "荷物をまとめているうちに、出発の時間になりました。",
      "kr": "짐을 싸는 동안 출발 시간이 되었습니다.",
      "words": [
        {
          "jp": "まとめる",
          "kr": "(짐을) 싸다, 정리하다"
        },
        {
          "jp": "～うちに",
          "kr": "～하는 동안에"
        }
      ]
    },
    {
      "id": 54,
      "jp": "この橋を渡ると、有名な神社があります。",
      "kr": "이 다리를 건너면 유명한 신사가 있습니다.",
      "words": [
        {
          "jp": "渡る",
          "kr": "건너다"
        },
        {
          "jp": "神社",
          "kr": "신사"
        }
      ]
    },
    {
      "id": 55,
      "jp": "旅行中は、なるべく現金を持ち歩かないようにしています。",
      "kr": "여행 중에는 되도록 현금을 가지고 다니지 않으려고 하고 있습니다.",
      "words": [
        {
          "jp": "なるべく",
          "kr": "되도록"
        },
        {
          "jp": "持ち歩く",
          "kr": "가지고 다니다"
        },
        {
          "jp": "～ないようにしている",
          "kr": "～하지 않으려고 하고 있다"
        }
      ]
    },
    {
      "id": 56,
      "jp": "天気が悪かったにもかかわらず、観光を楽しみました。",
      "kr": "날씨가 나빴음에도 불구하고 관광을 즐겼습니다.",
      "words": [
        {
          "jp": "～にもかかわらず",
          "kr": "～에도 불구하고"
        },
        {
          "jp": "観光",
          "kr": "관광"
        }
      ]
    },
    {
      "id": 57,
      "jp": "スーツケースが壊れて、修理してもらいました。",
      "kr": "여행 가방이 고장 나서 수리를 받았습니다.",
      "words": [
        {
          "jp": "壊れる",
          "kr": "고장 나다"
        },
        {
          "jp": "修理",
          "kr": "수리"
        }
      ]
    },
    {
      "id": 58,
      "jp": "有名な料理を食べないうちは、帰れない。",
      "kr": "유명한 요리를 먹기 전에는 돌아갈 수 없다.",
      "words": [
        {
          "jp": "～ないうちは",
          "kr": "～하기 전에는"
        }
      ]
    },
    {
      "id": 59,
      "jp": "道が分からなくて、通りかかった人に聞きました。",
      "kr": "길을 몰라서 지나가던 사람에게 물었습니다.",
      "words": [
        {
          "jp": "通りかかる",
          "kr": "지나가다"
        }
      ]
    },
    {
      "id": 60,
      "jp": "旅行の思い出を、写真に残しておきました。",
      "kr": "여행의 추억을 사진으로 남겨 두었습니다.",
      "words": [
        {
          "jp": "思い出",
          "kr": "추억"
        },
        {
          "jp": "残す",
          "kr": "남기다"
        }
      ]
    },
    {
      "id": 61,
      "jp": "この電車に乗れば、乗り換えずに行けます。",
      "kr": "이 전철을 타면 환승하지 않고 갈 수 있습니다.",
      "words": [
        {
          "jp": "乗り換える",
          "kr": "환승하다"
        },
        {
          "jp": "～ずに",
          "kr": "～하지 않고"
        }
      ]
    },
    {
      "id": 62,
      "jp": "空港に早めに着くように、家を出ました。",
      "kr": "공항에 일찍 도착할 수 있도록 집을 나섰습니다.",
      "words": [
        {
          "jp": "早めに",
          "kr": "일찌감치"
        }
      ]
    },
    {
      "id": 63,
      "jp": "現地では、日本語が通じないことが多いです。",
      "kr": "현지에서는 일본어가 통하지 않는 경우가 많습니다.",
      "words": [
        {
          "jp": "現地",
          "kr": "현지"
        },
        {
          "jp": "通じる",
          "kr": "통하다"
        },
        {
          "jp": "～ことが多い",
          "kr": "～경우가 많다"
        }
      ]
    },
    {
      "id": 64,
      "jp": "予約なしで行ったら、満席で入れませんでした。",
      "kr": "예약 없이 갔더니 만석이라 들어갈 수 없었습니다.",
      "words": [
        {
          "jp": "満席",
          "kr": "만석"
        }
      ]
    },
    {
      "id": 65,
      "jp": "天気予報が当たって、旅行中はずっと晴れでした。",
      "kr": "일기예보가 맞아서 여행하는 동안 계속 맑았습니다.",
      "words": [
        {
          "jp": "当たる",
          "kr": "맞다"
        }
      ]
    },
    {
      "id": 66,
      "jp": "この地方は、冬になると雪が多くなります。",
      "kr": "이 지방은 겨울이 되면 눈이 많이 옵니다.",
      "words": [
        {
          "jp": "地方",
          "kr": "지방"
        }
      ]
    },
    {
      "id": 67,
      "jp": "観光客が増えたことで、町がにぎやかになりました。",
      "kr": "관광객이 늘어나면서 마을이 활기차졌습니다.",
      "words": [
        {
          "jp": "増える",
          "kr": "늘다"
        },
        {
          "jp": "～ことで",
          "kr": "～함으로써, ～함으로 인해"
        }
      ]
    },
    {
      "id": 68,
      "jp": "荷物が重すぎて、持って歩けませんでした。",
      "kr": "짐이 너무 무거워서 들고 걸을 수 없었습니다.",
      "words": [
        {
          "jp": "持って歩く",
          "kr": "들고 걷다"
        }
      ]
    },
    {
      "id": 69,
      "jp": "電車が止まってしまって、駅で足止めされました。",
      "kr": "전철이 멈춰 버려서 역에서 발이 묶였습니다.",
      "words": [
        {
          "jp": "足止め",
          "kr": "발이 묶임, 이동하지 못함"
        }
      ]
    },
    {
      "id": 70,
      "jp": "せっかく来たのに、お寺は工事中でした。",
      "kr": "모처럼 왔는데 절은 공사 중이었습니다.",
      "words": [
        {
          "jp": "せっかく",
          "kr": "모처럼"
        },
        {
          "jp": "工事中",
          "kr": "공사 중"
        }
      ]
    },
    {
      "id": 71,
      "jp": "地図を見ながら歩いていたら、迷ってしまいました。",
      "kr": "지도를 보면서 걷다가 길을 잃고 말았습니다.",
      "words": [
        {
          "jp": "迷う",
          "kr": "헤매다, 길을 잃다"
        }
      ]
    },
    {
      "id": 72,
      "jp": "この店は、予約しないと入れないほど人気です。",
      "kr": "이 가게는 예약하지 않으면 들어갈 수 없을 정도로 인기가 많습니다.",
      "words": [
        {
          "jp": "～ないと",
          "kr": "～하지 않으면"
        },
        {
          "jp": "～ほど",
          "kr": "～정도로"
        }
      ]
    },
    {
      "id": 73,
      "jp": "旅行の計画を立てるのが、何より楽しい。",
      "kr": "여행 계획을 세우는 것이 무엇보다 즐겁다.",
      "words": [
        {
          "jp": "計画を立てる",
          "kr": "계획을 세우다"
        },
        {
          "jp": "何より",
          "kr": "무엇보다"
        }
      ]
    },
    {
      "id": 74,
      "jp": "パスポートの期限が切れていて、あわてました。",
      "kr": "여권의 유효기간이 만료되어 있어서 당황했습니다.",
      "words": [
        {
          "jp": "期限が切れる",
          "kr": "유효기간이 만료되다"
        },
        {
          "jp": "あわてる",
          "kr": "당황하다"
        }
      ]
    },
    {
      "id": 75,
      "jp": "観光名所を回るには、一日では足りません。",
      "kr": "관광 명소를 둘러보기에는 하루로 부족합니다.",
      "words": [
        {
          "jp": "名所",
          "kr": "명소"
        },
        {
          "jp": "回る",
          "kr": "돌다"
        },
        {
          "jp": "足りる",
          "kr": "충분하다"
        }
      ]
    },
    {
      "id": 76,
      "jp": "お土産を買いすぎて、荷物が重くなりました。",
      "kr": "기념품을 너무 많이 사서 짐이 무거워졌습니다.",
      "words": [
        {
          "jp": "お土産",
          "kr": "기념품, 선물"
        }
      ]
    },
    {
      "id": 77,
      "jp": "この宿は、料理がおいしいことで有名です。",
      "kr": "이 숙소는 음식이 맛있기로 유명합니다.",
      "words": [
        {
          "jp": "宿",
          "kr": "숙소"
        },
        {
          "jp": "～ことで有名",
          "kr": "～하기로 유명하다"
        }
      ]
    },
    {
      "id": 78,
      "jp": "飛行機の中では、ほとんど眠れませんでした。",
      "kr": "비행기 안에서는 거의 잠을 자지 못했습니다.",
      "words": [
        {
          "jp": "ほとんど",
          "kr": "거의"
        }
      ]
    },
    {
      "id": 79,
      "jp": "天気が心配でしたが、無事に登れてよかったです。",
      "kr": "날씨가 걱정되었지만 무사히 오를 수 있어서 다행이었습니다.",
      "words": [
        {
          "jp": "無事に",
          "kr": "무사히"
        }
      ]
    },
    {
      "id": 80,
      "jp": "現地のバスは、時間通りに来ないことが多いです。",
      "kr": "현지 버스는 제시간에 오지 않는 경우가 많습니다.",
      "words": [
        {
          "jp": "時間通り",
          "kr": "제시간에, 정시에"
        },
        {
          "jp": "～ことが多い",
          "kr": "～경우가 많다"
        }
      ]
    },
    {
      "id": 81,
      "jp": "せっかくだから、少し遠回りして景色を見よう。",
      "kr": "모처럼이니까 조금 돌아가서 경치를 보자.",
      "words": [
        {
          "jp": "せっかくだから",
          "kr": "모처럼이니까"
        },
        {
          "jp": "遠回り",
          "kr": "돌아감, 우회"
        },
        {
          "jp": "景色",
          "kr": "경치"
        }
      ]
    },
    {
      "id": 82,
      "jp": "チケットを予約しておいたおかげで、並ばずに済みました。",
      "kr": "티켓을 미리 예약해 둔 덕분에 줄을 서지 않아도 되었습니다.",
      "words": [
        {
          "jp": "～おかげで",
          "kr": "～덕분에"
        },
        {
          "jp": "～ずに済む",
          "kr": "～하지 않아도 되다"
        }
      ]
    },
    {
      "id": 83,
      "jp": "この町は、歩いて回れるくらい小さいです。",
      "kr": "이 마을은 걸어서 둘러볼 수 있을 정도로 작습니다.",
      "words": [
        {
          "jp": "～くらい",
          "kr": "～정도로"
        }
      ]
    },
    {
      "id": 84,
      "jp": "旅行に行くたびに、荷物が増えてしまいます。",
      "kr": "여행을 갈 때마다 짐이 늘어나 버립니다.",
      "words": [
        {
          "jp": "～たびに",
          "kr": "～할 때마다"
        },
        {
          "jp": "増える",
          "kr": "늘다"
        }
      ]
    },
    {
      "id": 85,
      "jp": "予定が詰まっていて、ゆっくりできませんでした。",
      "kr": "일정이 빡빡해서 느긋하게 쉴 수 없었습니다.",
      "words": [
        {
          "jp": "詰まる",
          "kr": "꽉 차다, 일정이 빡빡하다"
        }
      ]
    },
    {
      "id": 86,
      "jp": "この景色は、写真では伝わりません。",
      "kr": "이 경치는 사진만으로는 제대로 전해지지 않습니다.",
      "words": [
        {
          "jp": "景色",
          "kr": "경치"
        },
        {
          "jp": "伝わる",
          "kr": "전해지다"
        }
      ]
    },
    {
      "id": 87,
      "jp": "道が混んでいたせいで、到着が遅れました。",
      "kr": "길이 막힌 탓에 도착이 늦어졌습니다.",
      "words": [
        {
          "jp": "混む",
          "kr": "막히다"
        },
        {
          "jp": "～せいで",
          "kr": "～탓에"
        }
      ]
    },
    {
      "id": 88,
      "jp": "お寺に着くころには、日が暮れていました。",
      "kr": "절에 도착할 무렵에는 날이 저물어 있었습니다.",
      "words": [
        {
          "jp": "～ころには",
          "kr": "～할 무렵에는"
        },
        {
          "jp": "日が暮れる",
          "kr": "날이 저물다"
        }
      ]
    },
    {
      "id": 89,
      "jp": "現金が足りなくなって、両替しました。",
      "kr": "현금이 부족해져서 환전했습니다.",
      "words": [
        {
          "jp": "足りる",
          "kr": "충분하다"
        },
        {
          "jp": "～なくなる",
          "kr": "～하지 않게 되다"
        },
        {
          "jp": "両替",
          "kr": "환전"
        }
      ]
    },
    {
      "id": 90,
      "jp": "旅行の疲れが取れるまで、しばらく休みたい。",
      "kr": "여행 피로가 풀릴 때까지 잠시 쉬고 싶다.",
      "words": [
        {
          "jp": "疲れが取れる",
          "kr": "피로가 풀리다"
        },
        {
          "jp": "しばらく",
          "kr": "잠시"
        }
      ]
    },
    {
      "id": 91,
      "jp": "早めに予約したから、いい席が取れました。",
      "kr": "일찍 예약해서 좋은 자리를 잡을 수 있었습니다.",
      "words": [
        {
          "jp": "早めに",
          "kr": "일찌감치"
        },
        {
          "jp": "席が取れる",
          "kr": "자리를 잡다"
        }
      ]
    },
    {
      "id": 92,
      "jp": "この道は、車が通れないほど狭いです。",
      "kr": "이 길은 차가 지나갈 수 없을 정도로 좁습니다.",
      "words": [
        {
          "jp": "～ほど",
          "kr": "～정도로"
        }
      ]
    },
    {
      "id": 93,
      "jp": "有名な観光地だけあって、とても混んでいました。",
      "kr": "유명한 관광지인 만큼 매우 붐볐습니다.",
      "words": [
        {
          "jp": "～だけあって",
          "kr": "～인 만큼"
        },
        {
          "jp": "観光地",
          "kr": "관광지"
        },
        {
          "jp": "混む",
          "kr": "붐비다"
        }
      ]
    },
    {
      "id": 94,
      "jp": "電車に乗る前に、切符を買っておこう。",
      "kr": "전철을 타기 전에 표를 사 두자.",
      "words": [
        {
          "jp": "切符",
          "kr": "표"
        }
      ]
    },
    {
      "id": 95,
      "jp": "天気に恵まれて、最高の旅になりました。",
      "kr": "날씨가 좋아서 최고의 여행이 되었습니다.",
      "words": [
        {
          "jp": "恵まれる",
          "kr": "좋은 조건을 얻다, 혜택을 받다"
        },
        {
          "jp": "旅",
          "kr": "여행"
        }
      ]
    },
    {
      "id": 96,
      "jp": "荷物を減らすために、必要な物だけ持ってきました。",
      "kr": "짐을 줄이기 위해 필요한 것만 가져왔습니다.",
      "words": [
        {
          "jp": "減らす",
          "kr": "줄이다"
        }
      ]
    },
    {
      "id": 97,
      "jp": "迷ったときは、駅員に聞くのが一番ですよ。",
      "kr": "길을 잃었을 때는 역무원에게 묻는 것이 가장 좋아요.",
      "words": [
        {
          "jp": "迷う",
          "kr": "헤매다"
        },
        {
          "jp": "駅員",
          "kr": "역무원"
        }
      ]
    },
    {
      "id": 98,
      "jp": "せっかく予約したのに、行けなくなってしまいました。",
      "kr": "모처럼 예약했는데 갈 수 없게 되고 말았습니다.",
      "words": [
        {
          "jp": "せっかく",
          "kr": "모처럼"
        },
        {
          "jp": "行けなくなる",
          "kr": "못 가게 되다"
        }
      ]
    },
    {
      "id": 99,
      "jp": "この温泉に入るために、遠くから来ました。",
      "kr": "이 온천에 들어가기 위해 멀리서 왔습니다.",
      "words": [
        {
          "jp": "温泉に入る",
          "kr": "온천에 들어가다, 몸을 담그다"
        }
      ]
    },
    {
      "id": 100,
      "jp": "また来られるように、お金をためておこう。",
      "kr": "또 올 수 있도록 돈을 모아 두자.",
      "words": [
        {
          "jp": "ためる",
          "kr": "모으다"
        }
      ]
    }
  ]
}